htiger/__init__.py
htiger/app.ini
htiger/excel2vcf.py
htiger/template.xlsx
excel2vcf-1.0.3.dist-info/LICENSE
excel2vcf-1.0.3.dist-info/METADATA
excel2vcf-1.0.3.dist-info/WHEEL
excel2vcf-1.0.3.dist-info/entry_points.txt
excel2vcf-1.0.3.dist-info/top_level.txt
excel2vcf-1.0.3.dist-info/RECORD
